list/Lib/site-packages/_virtualenv.py
list/Scripts/activate_this.py
pyvy/__init__.py
pyvy/main.py
pyvy/core/command_runner.py
pyvy/core/env_manager.py
pyvy/core/module_manager.py
pyvy/core/python_manager.py
pyvy/core/utils.py
pyvy-0.1.2.2.dist-info/METADATA
pyvy-0.1.2.2.dist-info/WHEEL
pyvy-0.1.2.2.dist-info/entry_points.txt
pyvy-0.1.2.2.dist-info/RECORD
