Metadata-Version: 2.4
Name: PYVY
Version: 0.1.2.2
Summary: A modern Python environment manager with a clean GUI. Manage virtual environments, modules, and Python versions effortlessly — powered by uv
Project-URL: Homepage, https://github.com/jyup-escape/PYVY
Project-URL: Bug Tracker, https://github.com/jyup-escape/PYVY/issues
Author-email: Ito Keisuke <ksk_ito.7217@icloud.com>
Classifier: License :: OSI Approved :: MIT License
Classifier: Operating System :: OS Independent
Classifier: Programming Language :: Python :: 3
Requires-Python: >=3.10
